rofi_menu/__init__.py
rofi_menu/constants.py
rofi_menu/contrib/__init__.py
rofi_menu/contrib/monitor.py
rofi_menu/contrib/shell.py
rofi_menu/contrib/touchpad.py
rofi_menu/main.py
rofi_menu/menu.py
rofi_menu/rofi_mode/__init__.py
rofi_menu/rofi_mode/rofi_mode_15.py
rofi_menu/rofi_mode/rofi_mode_16.py
rofi_menu/session.py
rofi_menu-0.5.1.dist-info/WHEEL
rofi_menu-0.5.1.dist-info/METADATA
rofi_menu-0.5.1.dist-info/RECORD
