Metadata-Version: 2.1
Name: rofi-menu
Version: 0.5.1
Summary: Create rofi menus via python
Home-page: https://github.com/miphreal/python-rofi-menu
License: MIT
Keywords: menu,rofi,rofi-mode
Author: miphreal
Author-email: miphreal@gmail.com
Requires-Python: >=3.6,<4.0
Classifier: License :: OSI Approved :: MIT License
Classifier: Programming Language :: Python :: 3
Classifier: Programming Language :: Python :: 3.6
Classifier: Programming Language :: Python :: 3.7
Classifier: Programming Language :: Python :: 3.8
Project-URL: Documentation, https://github.com/miphreal/python-rofi-menu
Project-URL: Repository, https://github.com/miphreal/python-rofi-menu
